pilcord/__init__.py
pilcord/assets/curveborder.png
pilcord/assets/curvedoverlay.png
pilcord/assets/fight.jpeg
pilcord/assets/levelfont.otf
pilcord/assets/mask_circle.jpg
pilcord/assets/overlay1.png
pilcord/assets/overlay2.png
pilcord/assets/overlay3.png
pilcord/assets/overlay4.png
pilcord/assets/rip.png
pilcord/assets/uwu_mask.png
pilcord/error.py
pilcord/meme.py
pilcord/ranking_card.py
pilcord-1.0.1.dist-info/WHEEL
pilcord-1.0.1.dist-info/METADATA
pilcord-1.0.1.dist-info/RECORD
