Metadata-Version: 2.1
Name: pilcord
Version: 1.0.1
Summary: A library rich with many image generation funcitons powered by PIL for your discord bot such as leveling, welcome card and meme generation!
License: MIT
Keywords: discord,leveling,card,image,discord.py,disnake,nextcord,rank,ranking,level,discord-bot,bot,discord-leveling,level-card,discord-leveling-card,discord-rank-card,meme-generation,pillow,pil,discord-image-generation,discord-meme-generation,discord-image,discord-meme,pycord,discord-rank,discord-welcome-card,welcome-card,welcome,discord-welcome-bot,discord-welcome-card
Author: Reset
Author-email: resetwastakenwastaken@gmail.com
Requires-Python: >=3.9,<4.0
Classifier: License :: OSI Approved :: MIT License
Classifier: Programming Language :: Python :: 3
Classifier: Programming Language :: Python :: 3.10
Classifier: Programming Language :: Python :: 3.9
Requires-Dist: Pillow (>=9.2.0,<10.0.0)
Requires-Dist: aiohttp (>=3.8.1,<4.0.0)
